pywundasmart/__init__.py
pywundasmart/functions.py
pywundasmart-0.0.5.dist-info/METADATA
pywundasmart-0.0.5.dist-info/WHEEL
pywundasmart-0.0.5.dist-info/licenses/LICENSE
pywundasmart-0.0.5.dist-info/RECORD
